cowexcept/__init__.py
cowexcept/auto.py
cowexcept-1.3.2.dist-info/licenses/LICENSE
cowexcept-1.3.2.dist-info/METADATA
cowexcept-1.3.2.dist-info/WHEEL
cowexcept-1.3.2.dist-info/top_level.txt
cowexcept-1.3.2.dist-info/RECORD
