Metadata-Version: 2.4
Name: cowexcept
Version: 1.3.2
Summary: Spice up those exceptions with cowexcept!
Author: James Finnie-Ansley
License-Expression: Apache-2.0
Project-URL: repository, https://codeberg.org/jamesansley/cowexcept
Keywords: cowsay
Requires-Python: >=3.8
License-File: LICENSE
Requires-Dist: python-cowsay>=1.2.2
Dynamic: license-file
